README.md
setup.cfg
setup.py
shakhbanov/__init__.py
shakhbanov.egg-info/PKG-INFO
shakhbanov.egg-info/SOURCES.txt
shakhbanov.egg-info/dependency_links.txt
shakhbanov.egg-info/requires.txt
shakhbanov.egg-info/top_level.txt
shakhbanov/cleaner/__init__.py
shakhbanov/cleaner/cleaner.py
shakhbanov/cluster/__init__.py
shakhbanov/cluster/cluster.py
shakhbanov/forecast/__init__.py
shakhbanov/forecast/forecast.py
shakhbanov/gapfiller/__init__.py
shakhbanov/gapfiller/gapfiller.py
shakhbanov/kalman_gap_filler/__init__.py
shakhbanov/kalman_gap_filler/kalman_gap_filler.py
shakhbanov/metrics/__init__.py
shakhbanov/metrics/metrics.py
shakhbanov/tsf/__init__.py
shakhbanov/tsf/tsf.py