Metadata-Version: 2.1
Name: shakhbanov
Version: 1.2.9
Summary: ML tools for time series
Home-page: https://shakhbanov.org
Download-URL: https://github.com/shakhbanov/shakhbanov/archive/refs/heads/main.zip
Author: Zurab Shakhbanov
Author-email: zurab@shakhbanov.ru
Project-URL: GitHub, https://github.com/shakhbanov/shakhbanov
Classifier: Programming Language :: Python :: 3
Classifier: License :: OSI Approved :: MIT License
Classifier: Operating System :: OS Independent
Requires-Python: >=3.6
Requires-Dist: numpy
Requires-Dist: pandas
Requires-Dist: matplotlib
Requires-Dist: tqdm
Requires-Dist: typing
Requires-Dist: joblib
Requires-Dist: prophet
Requires-Dist: lightgbm
Requires-Dist: holidays
Requires-Dist: scikit-learn
Requires-Dist: pykalman
Requires-Dist: scipy
Requires-Dist: statsmodels
Requires-Dist: tslearn
Requires-Dist: optuna
